adder.v
// Adder circuit
// sets gate delays
`define AND and #50
`define XOR xor #50
`define NOT not #50
`define OR or #50

module didOverflow
(
    output overflow,
    input a, 
    input b, 
    input s
); 
//this module determines if a signal overflows
// it requires the most significant bit of the two things being added together as well as the most significant bit of the sum
// this is only relevant when you are doing signed addition
	wire notA;
	wire notB;
	wire notS;
    wire aAndB;
    wire notaAndNotb;
    wire negToPos;
    wire posToNeg;

    `NOT aNot(notA, a);
    `NOT bNot(notB, b);
    `NOT sNot(notS, s);

    `AND andab(aAndB, a, b);
    `AND andabNot(notaAndNotb, notA, notB);

    `AND andSwitch1(negToPos, aAndB, notS); //if the most significant bit of a and b were both 0 and the most significant big of the sum was 1, the inputs were both positive and the outpus was negative
    `AND andSwitch2(posToNeg, notaAndNotb, s); // this is the same as the above line but from positive to negative

    `OR orGate(overflow, negToPos, posToNeg); 

endmodule

module structuralFullAdder
(
    output sum, 
    output carryout,
    input a, 
    input b, 
    input carryin
);
// this is our full adder unit that can add two one bit numbers together
    wire xAorB;
    wire AandB;
    wire xAorBandCin;

    `XOR  xorgate(xAorB, a, b);  // OR gate produces AorB from A and B
    `XOR  xorgate1(sum, xAorB, carryin);
    `AND  andgate(AandB, a, b);
    `AND  andgate1(xAorBandCin, xAorB, carryin);
    `OR   orgate(carryout, AandB, xAorBandCin);
    
endmodule

module FullAdder4bit
(
  output[3:0] sum,  // 2's complement sum of a and b
  output carryout,  // Carry out of the summation of a and b
  output overflow,  // True if the calculation resulted in an overflow
  input[3:0] a,     // First operand in 2's complement format
  input[3:0] b      // Second operand in 2's complement format
);
	wire carry01; //these are the connecting carries between the full adders
	wire carry12; // ex: carry01 is the cary out from the 0th full adder and the carry in to the 1st full adder
	wire carry23;

	// we can just connect 4 full adders together to get a four bit adder

	structuralFullAdder add0 (
	  .sum (sum[0]),
	  .carryout (carry01),
	  .a (a[0]),
	  .b (b[0]),
	  .carryin (1'b0)
	);
	structuralFullAdder add1 (
	  .sum (sum[1]),
	  .carryout (carry12),
	  .a (a[1]),
	  .b (b[1]),
	  .carryin (carry01)
	);
	structuralFullAdder add2 (
	  .sum (sum[2]),
	  .carryout (carry23),
	  .a (a[2]),
	  .b (b[2]),
	  .carryin (carry12)
	);
	structuralFullAdder add3 (
	  .sum (sum[3]),
	  .carryout (carryout),
	  .a (a[3]),
	  .b (b[3]),
	  .carryin (carry23)
	);
	// this part calculates the overflow seperately
	didOverflow over1 ( 
	  .overflow (overflow),
	  .a (a[3]),
	  .b (b[3]),
	  .s (sum[3])
	);
endmodule

adder.t.v
// Adder testbench
`timescale 1 ns / 1 ps
`include "adder.v"

module testFullAdder();
    reg[3:0] a;
    reg[3:0] b;
    wire[3:0] sum;
    wire carryout;
    wire overflow;

    //behavioralFullAdder adder (sum, carryout, a, b, carryin);
    FullAdder4bit adder (sum, carryout, overflow, a, b);

    initial begin

    	$dumpfile("adder.vcd");
    	$dumpvars(0,adder);

        $display("  A    B   | Sum  | Cout | Overflow |   ExSum  | ExCout | ExOverflow");
        a=4'b0001;b=4'b0000; #1000
        $display(" %b%b%b%b %b%b%b%b | %b%b%b%b |  %b   |     %b    |   0001   |    0   |     0", a[3], a[2], a[1], a[0] , b[3], b[2], b[1], b[0], sum[3], sum[2], sum[1], sum[0], carryout, overflow);
        a=4'b0000;b=4'b1100; #1000
        $display(" %b%b%b%b %b%b%b%b | %b%b%b%b |  %b   |     %b    |   1100   |    0   |     0", a[3], a[2], a[1], a[0] , b[3], b[2], b[1], b[0], sum[3], sum[2], sum[1], sum[0], carryout, overflow);
        a=4'b0111;b=4'b0111; #1000
        $display(" %b%b%b%b %b%b%b%b | %b%b%b%b |  %b   |     %b    |   1110   |    0   |     1", a[3], a[2], a[1], a[0] , b[3], b[2], b[1], b[0], sum[3], sum[2], sum[1], sum[0], carryout, overflow);
        a=4'b1000;b=4'b1000; #1000
        $display(" %b%b%b%b %b%b%b%b | %b%b%b%b |  %b   |     %b    |   0000   |    1   |     1", a[3], a[2], a[1], a[0] , b[3], b[2], b[1], b[0], sum[3], sum[2], sum[1], sum[0], carryout, overflow);
        a=4'b1111;b=4'b0111; #1000
        $display(" %b%b%b%b %b%b%b%b | %b%b%b%b |  %b   |     %b    |   0110   |    1   |     0", a[3], a[2], a[1], a[0] , b[3], b[2], b[1], b[0], sum[3], sum[2], sum[1], sum[0], carryout, overflow);
        a=4'b0011;b=4'b1101; #1000
        $display(" %b%b%b%b %b%b%b%b | %b%b%b%b |  %b   |     %b    |   0000   |    1   |     0", a[3], a[2], a[1], a[0] , b[3], b[2], b[1], b[0], sum[3], sum[2], sum[1], sum[0], carryout, overflow);
        a=4'b1111;b=4'b1111; #1000
        $display(" %b%b%b%b %b%b%b%b | %b%b%b%b |  %b   |     %b    |   1110   |    1   |     0", a[3], a[2], a[1], a[0] , b[3], b[2], b[1], b[0], sum[3], sum[2], sum[1], sum[0], carryout, overflow);
        a=4'b0001;b=4'b0001; #1000
        $display(" %b%b%b%b %b%b%b%b | %b%b%b%b |  %b   |     %b    |   0010   |    0   |     0", a[3], a[2], a[1], a[0] , b[3], b[2], b[1], b[0], sum[3], sum[2], sum[1], sum[0], carryout, overflow);
        a=4'b0010;b=4'b0001; #1000
        $display(" %b%b%b%b %b%b%b%b | %b%b%b%b |  %b   |     %b    |   0011   |    0   |     0", a[3], a[2], a[1], a[0] , b[3], b[2], b[1], b[0], sum[3], sum[2], sum[1], sum[0], carryout, overflow);
        a=4'b0100;b=4'b0101; #1000
        $display(" %b%b%b%b %b%b%b%b | %b%b%b%b |  %b   |     %b    |   1001   |    0   |     1", a[3], a[2], a[1], a[0] , b[3], b[2], b[1], b[0], sum[3], sum[2], sum[1], sum[0], carryout, overflow);
        a=4'b1110;b=4'b1101; #1000
        $display(" %b%b%b%b %b%b%b%b | %b%b%b%b |  %b   |     %b    |   1011   |    1   |     0", a[3], a[2], a[1], a[0] , b[3], b[2], b[1], b[0], sum[3], sum[2], sum[1], sum[0], carryout, overflow);
        a=4'b1001;b=4'b1000; #1000
        $display(" %b%b%b%b %b%b%b%b | %b%b%b%b |  %b   |     %b    |   0001   |    1   |     1", a[3], a[2], a[1], a[0] , b[3], b[2], b[1], b[0], sum[3], sum[2], sum[1], sum[0], carryout, overflow);
        a=4'b1011;b=4'b1010; #1000
        $display(" %b%b%b%b %b%b%b%b | %b%b%b%b |  %b   |     %b    |   0001   |    1   |     1", a[3], a[2], a[1], a[0] , b[3], b[2], b[1], b[0], sum[3], sum[2], sum[1], sum[0], carryout, overflow);
        a=4'b1101;b=4'b0111; #1000
        $display(" %b%b%b%b %b%b%b%b | %b%b%b%b |  %b   |     %b    |   0100   |    1   |     0", a[3], a[2], a[1], a[0] , b[3], b[2], b[1], b[0], sum[3], sum[2], sum[1], sum[0], carryout, overflow);
        a=4'b0001;b=4'b1100; #1000
        $display(" %b%b%b%b %b%b%b%b | %b%b%b%b |  %b   |     %b    |   1101   |    0   |     0", a[3], a[2], a[1], a[0] , b[3], b[2], b[1], b[0], sum[3], sum[2], sum[1], sum[0], carryout, overflow);
        a=4'b0010;b=4'b1010; #1000
        $display(" %b%b%b%b %b%b%b%b | %b%b%b%b |  %b   |     %b    |   1100   |    0   |     0", a[3], a[2], a[1], a[0] , b[3], b[2], b[1], b[0], sum[3], sum[2], sum[1], sum[0], carryout, overflow);

    end
endmodule

adder.vcd
$date
	Tue Sep 25 16:45:03 2018
$end
$version
	Icarus Verilog
$end
$timescale
	1ps
$end
$scope module testFullAdder $end
$scope module adder $end
$var wire 4 ! a [3:0] $end
$var wire 4 " b [3:0] $end
$var wire 4 # sum [3:0] $end
$var wire 1 $ overflow $end
$var wire 1 % carryout $end
$var wire 1 & carry23 $end
$var wire 1 ' carry12 $end
$var wire 1 ( carry01 $end
$scope module add0 $end
$var wire 1 ) AandB $end
$var wire 1 * a $end
$var wire 1 + b $end
$var wire 1 , carryin $end
$var wire 1 ( carryout $end
$var wire 1 - sum $end
$var wire 1 . xAorB $end
$var wire 1 / xAorBandCin $end
$upscope $end
$scope module add1 $end
$var wire 1 0 AandB $end
$var wire 1 1 a $end
$var wire 1 2 b $end
$var wire 1 ( carryin $end
$var wire 1 ' carryout $end
$var wire 1 3 sum $end
$var wire 1 4 xAorB $end
$var wire 1 5 xAorBandCin $end
$upscope $end
$scope module add2 $end
$var wire 1 6 AandB $end
$var wire 1 7 a $end
$var wire 1 8 b $end
$var wire 1 ' carryin $end
$var wire 1 & carryout $end
$var wire 1 9 sum $end
$var wire 1 : xAorB $end
$var wire 1 ; xAorBandCin $end
$upscope $end
$scope module add3 $end
$var wire 1 < AandB $end
$var wire 1 = a $end
$var wire 1 > b $end
$var wire 1 & carryin $end
$var wire 1 % carryout $end
$var wire 1 ? sum $end
$var wire 1 @ xAorB $end
$var wire 1 A xAorBandCin $end
$upscope $end
$scope module over1 $end
$var wire 1 B a $end
$var wire 1 C aAndB $end
$var wire 1 D b $end
$var wire 1 E negToPos $end
$var wire 1 F notA $end
$var wire 1 G notB $end
$var wire 1 H notS $end
$var wire 1 I notaAndNotb $end
$var wire 1 $ overflow $end
$var wire 1 J posToNeg $end
$var wire 1 K s $end
$upscope $end
$upscope $end
$upscope $end
$enddefinitions $end
#0
$dumpvars
xK
xJ
xI
xH
xG
xF
xE
0D
xC
0B
xA
x@
x?
0>
0=
x<
x;
x:
x9
08
07
x6
x5
x4
x3
02
01
x0
x/
x.
x-
0,
0+
1*
x)
x(
x'
x&
x%
x$
bx #
b0 "
b1 !
$end
#50000
1G
1.
0)
04
00
0:
06
0@
0<
1F
0C
0/
#100000
bx1 #
1-
05
0;
0A
1I
0E
0(
#150000
0'
0&
0%
bx01 #
03
#200000
0K
09
b1 #
0?
#250000
1H
0J
#300000
0$
#1000000
18
1>
1D
0*
b1100 "
b0 !
#1050000
1:
1@
0G
0.
#1100000
1K
19
1?
0I
b1100 #
0-
#1150000
0H
#2000000
1+
12
0>
0D
1*
11
17
b111 "
b111 !
#2050000
0@
1G
1)
10
0:
16
#2100000
0K
0?
1I
1(
1'
b0 #
09
1&
#2150000
1K
1H
13
19
b1110 #
1?
#2200000
0H
1J
#2250000
1$
#3000000
0+
02
08
1>
1D
0*
01
07
1=
1B
b1000 "
b1000 !
#3050000
0G
0)
00
06
1<
0F
1C
#3100000
0(
0'
0&
1%
0I
#3150000
0K
03
09
b0 #
0?
0J
#3200000
1H
0$
#3250000
1E
#3300000
1$
#4000000
1+
12
18
0>
0D
1*
11
17
b111 "
b1111 !
#4050000
1@
0<
1G
0C
1)
10
16
#4100000
1K
b1000 #
1?
0%
0E
1(
1'
1&
#4150000
0K
0H
0$
13
19
b110 #
0?
1A
#4200000
1H
1%
#5000000
02
1>
1D
07
0=
0B
b1101 "
b11 !
#5050000
14
00
0G
1:
06
1F
#5100000
03
15
0'
b0 #
09
1;
0&
#5150000
1K
1'
19
0;
1&
b1100 #
1?
0A
#5200000
0K
0H
09
1;
0&
b0 #
0?
1A
0%
#5250000
1K
1H
1&
b1000 #
1?
0A
1%
#5300000
0K
0H
b0 #
0?
1A
0%
#5350000
1H
1%
#6000000
12
17
1=
1B
b1111 "
b1111 !
#6050000
04
10
0:
16
0@
1<
0F
1C
#6100000
1K
13
05
19
0;
b1110 #
1?
0A
1E
#6150000
0H
1$
#6200000
0E
#6250000
0$
#7000000
02
08
0>
0D
01
07
0=
0B
b1 "
b1 !
#7050000
1G
00
06
0<
1F
0C
#7100000
0'
0&
0%
1I
#7150000
0K
09
b10 #
0?
1J
#7200000
1H
0J
1$
#7250000
0$
#8000000
0*
11
b10 !
#8050000
1.
0)
14
#8100000
1-
0(
b1 #
03
15
#8150000
b11 #
13
05
1'
#8200000
0'
b111 #
19
#8250000
b11 #
09
#9000000
18
01
17
b101 "
b100 !
#9050000
04
16
#9100000
b1 #
03
1&
#9150000
1K
b1001 #
1?
#9200000
0H
1J
#9250000
1$
#10000000
1>
1D
11
1=
1B
b1101 "
b1110 !
#10050000
0G
14
1<
0F
1C
#10100000
b1011 #
13
1%
0I
#10150000
0J
#10200000
0$
#11000000
0+
08
1*
01
07
b1000 "
b1001 !
#11050000
04
06
#11100000
b1001 #
03
0&
#11150000
0K
b1 #
0?
#11200000
1H
#11250000
1E
#11300000
1$
#12000000
12
11
b1010 "
b1011 !
#12050000
10
#12100000
1'
#12150000
b101 #
19
#13000000
1+
18
0>
0D
01
17
b111 "
b1101 !
#13050000
0.
1)
1@
0<
1G
0C
14
00
16
#13100000
1K
0-
1(
1?
0%
0E
b1110 #
13
0'
1&
#13150000
0K
0H
03
15
0$
09
b0 #
0?
1A
#13200000
1H
1'
1%
#13250000
b100 #
19
#14000000
0+
02
1>
1D
07
0=
0B
b1100 "
b1 !
#14050000
1.
0)
04
0G
1:
06
1F
#14100000
1-
0(
13
05
b11 #
09
1;
0&
#14150000
1K
03
0'
1&
b1001 #
1?
0A
#14200000
0K
0H
19
0;
b101 #
0?
1A
0%
#14250000
1H
0&
1%
#14300000
1K
b1101 #
1?
0A
#14350000
0H
0%
#15000000
12
08
0*
11
b1010 "
b10 !
#15050000
0:
0.
10
#15100000
09
b1000 #
0-
1'
#15150000
b1100 #
19
