adder.v
// Adder circuit

`define AND and #50
`define OR or #50
`define XOR xor #50
`define NOT not #50

module didOverflow
(
    output overflow,
    input a, 
    input b, 
    input s
);
	wire notA;
	wire notB;
	wire notS;
    wire aAndB;
    wire notaAndNotb;
    wire negToPos;
    wire posToNeg;

    `NOT aNot(notA, a);
    `NOT bNot(notB, b);
    `NOT sNot(notS, s);

    `AND andab(aAndB, a, b);
    `AND andabNot(notaAndNotb, notA, notB);

    `AND andSwitch1(negToPos, aAndB, notS);
    `AND andSwitch2(posToNeg, notaAndNotb, s);

    `OR orGate(overflow, negToPos, posToNeg);

endmodule

module structuralFullAdder
(
    output sum, 
    output carryout,
    input a, 
    input b, 
    input carryin
);
    wire andab, andbIn, andaIn;
    wire orab, orbIn;
    wire orOut;

    `AND andAB(andab, a, b);
    `AND andBIN(andbIn, b, carryin);
    `AND andAIN(andaIn, a, carryin);

    `OR or1(orOut, andab, andbIn);
    `OR or2(carryout, orOut, andaIn);


    `XOR xor1(orab, a, b);
    `XOR xor2(sum, orab, carryin); 
endmodule

module FullAdder4bit
(
  output[3:0] sum,  // 2's complement sum of a and b
  output carryout,  // Carry out of the summation of a and b
  output overflow,  // True if the calculation resulted in an overflow
  input[3:0] a,     // First operand in 2's complement format
  input[3:0] b      // Second operand in 2's complement format
);
	wire carry01;
	wire carry12;
	wire carry23;

	structuralFullAdder add0 (
	  .sum (sum[0]),
	  .carryout (carry01),
	  .a (a[0]),
	  .b (b[0]),
	  .carryin (1'b0)
	);
	structuralFullAdder add1 (
	  .sum (sum[1]),
	  .carryout (carry12),
	  .a (a[1]),
	  .b (b[1]),
	  .carryin (carry01)
	);
	structuralFullAdder add2 (
	  .sum (sum[2]),
	  .carryout (carry23),
	  .a (a[2]),
	  .b (b[2]),
	  .carryin (carry12)
	);
	structuralFullAdder add3 (
	  .sum (sum[3]),
	  .carryout (carryout),
	  .a (a[3]),
	  .b (b[3]),
	  .carryin (carry23)
	);
	didOverflow over1 (
	  .overflow (overflow),
	  .a (a[3]),
	  .b (b[3]),
	  .s (sum[3])
	);
endmodule

adder.t.v
// Adder testbench
`timescale 1 ns / 1 ps
`include "adder.v"

module testFullAdder();
    reg[3:0] a;
    reg[3:0] b;
    wire[3:0] sum;
    wire carryout;
    wire overflow;

    //behavioralFullAdder adder (sum, carryout, a, b, carryin);
    FullAdder4bit adder (sum, carryout, overflow, a, b);

    initial begin

    	$dumpfile("adder.vcd");
    	$dumpvars(0,adder);

        $display("  A    B   | Sum  | Cout | Overflow | ExSum | ExCout | ExOverflow");
        a=4'b0111;b=4'b0001; #1000
        $display(" %b%b%b%b %b%b%b%b | %b%b%b%b |  %b   |     %b    |   0   |    0   |     0", a[3], a[2], a[1], a[0] , b[3], b[2], b[1], b[0], sum[3], sum[2], sum[1], sum[0], carryout, overflow);
    end
endmodule

adder.vcd
$date
	Sun Sep 23 22:21:30 2018
$end
$version
	Icarus Verilog
$end
$timescale
	1ps
$end
$scope module testFullAdder $end
$scope module adder $end
$var wire 4 ! a [3:0] $end
$var wire 4 " b [3:0] $end
$var wire 4 # sum [3:0] $end
$var wire 1 $ overflow $end
$var wire 1 % carryout $end
$var wire 1 & carry23 $end
$var wire 1 ' carry12 $end
$var wire 1 ( carry01 $end
$scope module add0 $end
$var wire 1 ) a $end
$var wire 1 * andaIn $end
$var wire 1 + andab $end
$var wire 1 , andbIn $end
$var wire 1 - b $end
$var wire 1 . carryin $end
$var wire 1 ( carryout $end
$var wire 1 / orOut $end
$var wire 1 0 orab $end
$var wire 1 1 sum $end
$upscope $end
$scope module add1 $end
$var wire 1 2 a $end
$var wire 1 3 andaIn $end
$var wire 1 4 andab $end
$var wire 1 5 andbIn $end
$var wire 1 6 b $end
$var wire 1 ( carryin $end
$var wire 1 ' carryout $end
$var wire 1 7 orOut $end
$var wire 1 8 orab $end
$var wire 1 9 sum $end
$upscope $end
$scope module add2 $end
$var wire 1 : a $end
$var wire 1 ; andaIn $end
$var wire 1 < andab $end
$var wire 1 = andbIn $end
$var wire 1 > b $end
$var wire 1 ' carryin $end
$var wire 1 & carryout $end
$var wire 1 ? orOut $end
$var wire 1 @ orab $end
$var wire 1 A sum $end
$upscope $end
$scope module add3 $end
$var wire 1 B a $end
$var wire 1 C andaIn $end
$var wire 1 D andab $end
$var wire 1 E andbIn $end
$var wire 1 F b $end
$var wire 1 & carryin $end
$var wire 1 % carryout $end
$var wire 1 G orOut $end
$var wire 1 H orab $end
$var wire 1 I sum $end
$upscope $end
$scope module over1 $end
$var wire 1 J a $end
$var wire 1 K aAndB $end
$var wire 1 L b $end
$var wire 1 M negToPos $end
$var wire 1 N notA $end
$var wire 1 O notB $end
$var wire 1 P notS $end
$var wire 1 Q notaAndNotb $end
$var wire 1 $ overflow $end
$var wire 1 R posToNeg $end
$var wire 1 S s $end
$upscope $end
$upscope $end
$upscope $end
$enddefinitions $end
#0
$dumpvars
xS
xR
xQ
xP
xO
xN
xM
0L
xK
0J
xI
xH
xG
0F
xE
xD
xC
0B
xA
x@
x?
0>
x=
x<
x;
1:
x9
x8
x7
06
x5
x4
x3
12
x1
x0
x/
0.
1-
x,
x+
x*
1)
x(
x'
x&
x%
x$
bx #
b1 "
b111 !
$end
#50000
05
0=
0E
1O
1+
00
04
18
0<
1@
0D
0C
0H
1N
0K
0,
0*
#100000
bx0 #
01
07
0?
0G
1Q
0M
1/
#150000
0%
1(
#200000
13
bx00 #
09
#250000
1'
#300000
1;
bx000 #
0A
#350000
1&
#400000
1S
b1000 #
1I
#450000
0P
1R
#500000
1$
